reachability/__init__.py
reachability/onlinecheck.py
reachability/reachability.py
reachability/repeat.py
reachability-0.1.4.dist-info/LICENSE
reachability-0.1.4.dist-info/METADATA
reachability-0.1.4.dist-info/WHEEL
reachability-0.1.4.dist-info/top_level.txt
reachability-0.1.4.dist-info/RECORD
