Metadata-Version: 2.1
Name: reachability
Version: 0.1.4
Summary: Monitor and observe Online Reachability, and react to status changes as necessary.
Home-page: https://github.com/glenncalleja/reachability
Author: Glenn Calleja Frendo
Author-email: glenncal@gmail.com
License: UNKNOWN
Keywords: online reachability status check connectivity
Platform: UNKNOWN
Classifier: Programming Language :: Python :: 3
Classifier: License :: OSI Approved :: MIT License
Classifier: Operating System :: OS Independent
Requires-Python: >=3.6
